odoo/addons/stock_vlm_mgmt_kardex/README.rst
odoo/addons/stock_vlm_mgmt_kardex/__init__.py
odoo/addons/stock_vlm_mgmt_kardex/__manifest__.py
odoo/addons/stock_vlm_mgmt_kardex/i18n/it.po
odoo/addons/stock_vlm_mgmt_kardex/i18n/stock_vlm_mgmt_kardex.pot
odoo/addons/stock_vlm_mgmt_kardex/models/__init__.py
odoo/addons/stock_vlm_mgmt_kardex/models/kardex_request.py
odoo/addons/stock_vlm_mgmt_kardex/models/stock_location.py
odoo/addons/stock_vlm_mgmt_kardex/readme/CONTRIBUTORS.rst
odoo/addons/stock_vlm_mgmt_kardex/readme/DESCRIPTION.rst
odoo/addons/stock_vlm_mgmt_kardex/static/description/icon.png
odoo/addons/stock_vlm_mgmt_kardex/static/description/index.html
odoo_addon_stock_vlm_mgmt_kardex-16.0.1.0.0.5.dist-info/METADATA
odoo_addon_stock_vlm_mgmt_kardex-16.0.1.0.0.5.dist-info/WHEEL
odoo_addon_stock_vlm_mgmt_kardex-16.0.1.0.0.5.dist-info/top_level.txt
odoo_addon_stock_vlm_mgmt_kardex-16.0.1.0.0.5.dist-info/RECORD
